RocketCasing/RocketCasing.py
RocketCasing/__init__.py
RocketCasing/__main__.py
RocketCasing/materials.py
RocketCasing-1.3.18.dist-info/LICENSE.txt
RocketCasing-1.3.18.dist-info/METADATA
RocketCasing-1.3.18.dist-info/WHEEL
RocketCasing-1.3.18.dist-info/top_level.txt
RocketCasing-1.3.18.dist-info/RECORD
