Metadata-Version: 2.1
Name: RocketCasing
Version: 1.3.18
Summary: Programa baseado na planilha Casing de Richard Nakka para cálculo e design de pressão de ruptura de um foguete de motor sólido. Program based on Richard Nakka spreadsheet for design and burst pressure for solid rocket motor
Home-page: https://github.com/LucasValentimB/RocketCasing
Author: Lucas Valentim Câmara
Author-email: lucasbcamara@gmail.com
License: UNKNOWN
Keywords: casing,foguete,SRM,invólucro,pressão,Nakka
Platform: UNKNOWN
Classifier: Development Status :: 4 - Beta
Classifier: Intended Audience :: Developers
Classifier: Intended Audience :: Other Audience
Classifier: Topic :: Software Development :: Build Tools
Classifier: Topic :: Scientific/Engineering
Classifier: Topic :: Scientific/Engineering :: Physics
Classifier: License :: OSI Approved :: MIT License
Classifier: Programming Language :: Python :: 3
Classifier: Programming Language :: Python :: 3.6
Classifier: Programming Language :: Python :: 3.7
Classifier: Programming Language :: Python :: 3.8
Classifier: Programming Language :: Python :: 3.9
Classifier: Programming Language :: Python :: 3 :: Only
Requires-Python: >=3.6, <4
Requires-Dist: peppercorn
Requires-Dist: matplotlib
Requires-Dist: datetime
Provides-Extra: dev
Requires-Dist: check-manifest ; extra == 'dev'
Provides-Extra: test
Requires-Dist: coverage ; extra == 'test'
